cloudflare_images_mcp/__init__.py
cloudflare_images_mcp/__main__.py
cloudflare_images_mcp/add_image.py
cloudflare_images_mcp/context.py
cloudflare_images_mcp-0.1.0.dist-info/METADATA
cloudflare_images_mcp-0.1.0.dist-info/WHEEL
cloudflare_images_mcp-0.1.0.dist-info/entry_points.txt
cloudflare_images_mcp-0.1.0.dist-info/licenses/LICENSE
cloudflare_images_mcp-0.1.0.dist-info/RECORD
