Metadata-Version: 2.4
Name: cloudflare-images-mcp
Version: 0.1.0
Summary: Simple MCP server to add images to Cloudflare Images
Author-email: Philipp Eisen <hello@philippeisen.de>
License-File: LICENSE
Requires-Python: <3.13,>=3.10
Requires-Dist: httpx>=0.25.0
Requires-Dist: mcp>=1.6.0
